veoliAPI/__init__.py
veoliAPI/veoliAPI.py
veoliAPI-0.0.3.dist-info/LICENSE
veoliAPI-0.0.3.dist-info/METADATA
veoliAPI-0.0.3.dist-info/WHEEL
veoliAPI-0.0.3.dist-info/top_level.txt
veoliAPI-0.0.3.dist-info/RECORD
