Metadata-Version: 2.1
Name: veoliAPI
Version: 0.0.3
Summary: To get the monthly water consumption from the Veolia API
Home-page: https://github.com/CorentinGrard/VeoliAPI
Author: Corentin Grard
Author-email: corentin.grard@gmail.com
Classifier: Programming Language :: Python :: 3
Classifier: License :: OSI Approved :: MIT License
Classifier: Operating System :: OS Independent
Requires-Python: >=3.6
License-File: LICENSE
Requires-Dist: requests
